[{"BAS_DD":"20230615","IDX_CLSS":"KRX","IDX_NM":" \uc6b4\uc1a1","CLSPRC_IDX":951.96,"CMPPREVDD_IDX":"4.29","FLUC_RT":0.45,"OPNPRC_IDX":"952.88","HGPRC_IDX":"960.80","LWPRC_IDX":"950.18","ACC_TRDVOL":"9631737","ACC_TRDVAL":"170650485837","MKTCAP":"38961311740550","CMPPREVDD_IDX\t":4.29},{"BAS_DD":"20230615","IDX_CLSS":"KRX","IDX_NM":" \uacbd\uae30\uc18c\ube44\uc7ac","CLSPRC_IDX":1059.16,"CMPPREVDD_IDX":"-8.80","FLUC_RT":-0.82,"OPNPRC_IDX":"1068.47","HGPRC_IDX":"1071.68","LWPRC_IDX":"1056.43","ACC_TRDVOL":"8739030","ACC_TRDVAL":"282702007900","MKTCAP":"68316909591110","CMPPREVDD_IDX\t":-8.8},{"BAS_DD":"20230615","IDX_CLSS":"KRX","IDX_NM":" \ud544\uc218\uc18c\ube44\uc7ac","CLSPRC_IDX":1188.07,"CMPPREVDD_IDX":"0.97","FLUC_RT":0.08,"OPNPRC_IDX":"1188.27","HGPRC_IDX":"1200.47","LWPRC_IDX":"1185.70","ACC_TRDVOL":"9032852","ACC_TRDVAL":"373961779963","MKTCAP":"69839035083760","CMPPREVDD_IDX\t":0.97},{"BAS_DD":"20230615","IDX_CLSS":"KRX","IDX_NM":" \ubbf8\ub514\uc5b4&\uc5d4\ud130\ud14c\uc778\uba3c\ud2b8","CLSPRC_IDX":2105.85,"CMPPREVDD_IDX":"-10.19","FLUC_RT":-0.48,"OPNPRC_IDX":"2124.75","HGPRC_IDX":"2137.90","LWPRC_IDX":"2100.27","ACC_TRDVOL":"10729665","ACC_TRDVAL":"728691420270","MKTCAP":"123045690411540","CMPPREVDD_IDX\t":-10.19},{"BAS_DD":"20230615","IDX_CLSS":"KRX","IDX_NM":" \uc815\ubcf4\uae30\uc220","CLSPRC_IDX":1655.84,"CMPPREVDD_IDX":"7.26","FLUC_RT":0.44,"OPNPRC_IDX":"1659.83","HGPRC_IDX":"1668.33","LWPRC_IDX":"1639.48","ACC_TRDVOL":"70621731","ACC_TRDVAL":"3641816718674","MKTCAP":"678879073805900","CMPPREVDD_IDX\t":7.26},{"BAS_DD":"20230615","IDX_CLSS":"KRX","IDX_NM":" \uc720\ud2f8\ub9ac\ud2f0","CLSPRC_IDX":564.64,"CMPPREVDD_IDX":"-3.21","FLUC_RT":-0.57,"OPNPRC_IDX":"568.34","HGPRC_IDX":"570.13","LWPRC_IDX":"561.77","ACC_TRDVOL":"2627531","ACC_TRDVAL":"52844217290","MKTCAP":"16684622384900","CMPPREVDD_IDX\t":-3.21},{"BAS_DD":"20230615","IDX_CLSS":"KRX","IDX_NM":" 300 \uc815\ubcf4\uae30\uc220","CLSPRC_IDX":2688.8,"CMPPREVDD_IDX":"15.12","FLUC_RT":0.57,"OPNPRC_IDX":"2694.54","HGPRC_IDX":"2709.12","LWPRC_IDX":"2659.56","ACC_TRDVOL":"61821708","ACC_TRDVAL":"3433544176834","MKTCAP":"659277936833110","CMPPREVDD_IDX\t":15.12}]