[{"BAS_DD":"20230615","IDX_CLSS":"KRX","IDX_NM":" 300 \uae08\uc735","CLSPRC_IDX":748.98,"CMPPREVDD_IDX":"-4.23","FLUC_RT":-0.56,"OPNPRC_IDX":"753.57","HGPRC_IDX":"758.27","LWPRC_IDX":"747.55","ACC_TRDVOL":"12212963","ACC_TRDVAL":"313878389256","MKTCAP":"156638423601410","CMPPREVDD_IDX\t":-4.23},{"BAS_DD":"20230615","IDX_CLSS":"KRX","IDX_NM":" 300 \uc790\uc720\uc18c\ube44\uc7ac","CLSPRC_IDX":1447.07,"CMPPREVDD_IDX":"-8.19","FLUC_RT":-0.56,"OPNPRC_IDX":"1459.82","HGPRC_IDX":"1462.93","LWPRC_IDX":"1444.87","ACC_TRDVOL":"8820714","ACC_TRDVAL":"481805779860","MKTCAP":"169863837544090","CMPPREVDD_IDX\t":-8.19},{"BAS_DD":"20230615","IDX_CLSS":"KRX","IDX_NM":" 300 \uc0b0\uc5c5\uc7ac","CLSPRC_IDX":676.14,"CMPPREVDD_IDX":"0.47","FLUC_RT":0.07,"OPNPRC_IDX":"678.27","HGPRC_IDX":"681.02","LWPRC_IDX":"672.94","ACC_TRDVOL":"50329266","ACC_TRDVAL":"1627716746020","MKTCAP":"262656957223630","CMPPREVDD_IDX\t":0.47},{"BAS_DD":"20230615","IDX_CLSS":"KRX","IDX_NM":" 300 \ud5ec\uc2a4\ucf00\uc5b4","CLSPRC_IDX":2356.65,"CMPPREVDD_IDX":"-24.84","FLUC_RT":-1.04,"OPNPRC_IDX":"2386.80","HGPRC_IDX":"2388.18","LWPRC_IDX":"2339.84","ACC_TRDVOL":"15543566","ACC_TRDVAL":"716170917340","MKTCAP":"154387703572300","CMPPREVDD_IDX\t":-24.84},{"BAS_DD":"20230615","IDX_CLSS":"KRX","IDX_NM":" 300 \ucee4\ubba4\ub2c8\ucf00\uc774\uc158\uc11c\ube44\uc2a4","CLSPRC_IDX":1575.78,"CMPPREVDD_IDX":"-9.32","FLUC_RT":-0.59,"OPNPRC_IDX":"1590.94","HGPRC_IDX":"1599.60","LWPRC_IDX":"1572.53","ACC_TRDVOL":"12734952","ACC_TRDVAL":"776913005701","MKTCAP":"142767050649400","CMPPREVDD_IDX\t":-9.32},{"BAS_DD":"20230615","IDX_CLSS":"KRX","IDX_NM":" 300 \uc18c\uc7ac","CLSPRC_IDX":1978.36,"CMPPREVDD_IDX":"4.48","FLUC_RT":0.23,"OPNPRC_IDX":"1993.73","HGPRC_IDX":"2009.96","LWPRC_IDX":"1950.46","ACC_TRDVOL":"26293013","ACC_TRDVAL":"3096834736920","MKTCAP":"220345214586640","CMPPREVDD_IDX\t":4.48},{"BAS_DD":"20230615","IDX_CLSS":"KRX","IDX_NM":" 300 \ud544\uc218\uc18c\ube44\uc7ac","CLSPRC_IDX":1167.84,"CMPPREVDD_IDX":"1.64","FLUC_RT":0.14,"OPNPRC_IDX":"1167.35","HGPRC_IDX":"1180.35","LWPRC_IDX":"1165.04","ACC_TRDVOL":"8113488","ACC_TRDVAL":"358569570743","MKTCAP":"64060608031920","CMPPREVDD_IDX\t":1.64}]